sentio_prober_control/__init__.py
sentio_prober_control/Communication/CommunicatorBase.py
sentio_prober_control/Communication/CommunicatorGpib.py
sentio_prober_control/Communication/CommunicatorTcpIp.py
sentio_prober_control/Communication/CommunicatorVisa.py
sentio_prober_control/Communication/__init__.py
sentio_prober_control/Devices/GpibAdlinkDriver.py
sentio_prober_control/Devices/GpibNiDriver.py
sentio_prober_control/Devices/__init__.py
sentio_prober_control/Sentio/Compatibility.py
sentio_prober_control/Sentio/Enumerations.py
sentio_prober_control/Sentio/Helper.py
sentio_prober_control/Sentio/ProberBase.py
sentio_prober_control/Sentio/ProberSentio.py
sentio_prober_control/Sentio/Response.py
sentio_prober_control/Sentio/__init__.py
sentio_prober_control/Sentio/CommandGroups/AuxCleaningGroup.py
sentio_prober_control/Sentio/CommandGroups/AuxCommandGroup.py
sentio_prober_control/Sentio/CommandGroups/CommandGroupBase.py
sentio_prober_control/Sentio/CommandGroups/CompensationCommandGroup.py
sentio_prober_control/Sentio/CommandGroups/LoaderCommandGroup.py
sentio_prober_control/Sentio/CommandGroups/LoaderVirtualCarrierCommandGroup.py
sentio_prober_control/Sentio/CommandGroups/ModuleCommandGroupBase.py
sentio_prober_control/Sentio/CommandGroups/ProbeCommandGroup.py
sentio_prober_control/Sentio/CommandGroups/QAlibriaCommandGroup.py
sentio_prober_control/Sentio/CommandGroups/ScopeCommandGroup.py
sentio_prober_control/Sentio/CommandGroups/ServiceCommandGroup.py
sentio_prober_control/Sentio/CommandGroups/SetupCommandGroup.py
sentio_prober_control/Sentio/CommandGroups/SetupContactCounterCommandGroup.py
sentio_prober_control/Sentio/CommandGroups/SetupRemoteCommandGroup.py
sentio_prober_control/Sentio/CommandGroups/SiPHCommandGroup.py
sentio_prober_control/Sentio/CommandGroups/StageCommandGroup.py
sentio_prober_control/Sentio/CommandGroups/StatusCommandGroup.py
sentio_prober_control/Sentio/CommandGroups/VisionCameraCommandGroup.py
sentio_prober_control-25.2.0.dist-info/licenses/LICENSE
sentio_prober_control-25.2.0.dist-info/METADATA
sentio_prober_control-25.2.0.dist-info/WHEEL
sentio_prober_control-25.2.0.dist-info/top_level.txt
sentio_prober_control-25.2.0.dist-info/RECORD
