Metadata-Version: 2.4
Name: sentio-prober-control
Version: 25.2.0
Summary: MPI Sentio Prober Control - Python Bindings
Author-email: Ingo Berg <ingo.berg@atv-systems.de>
Project-URL: Homepage, https://ast.mpi-corporation.com/
Project-URL: Bug Tracker, https://github.com/SentioProberDev/SentioProberControl/issues
Classifier: Programming Language :: Python :: 3
Classifier: Operating System :: OS Independent
Classifier: Development Status :: 5 - Production/Stable
Classifier: Environment :: Console
Classifier: License :: Other/Proprietary License
Classifier: Natural Language :: English
Classifier: Topic :: Scientific/Engineering
Requires-Python: >=3.7
License-File: LICENSE
Requires-Dist: pyvisa
Requires-Dist: deprecated
Dynamic: license-file
